Metadata-Version: 2.1
Name: owm-api-dftorres
Version: 0.0.1
Summary: Obtener la información actual y la previsión del tiempo desde open weather map api
Home-page: https://github.com/dftorres/mi_proyecto
Author: Daniel Felipe Torres
Author-email: dafetohe2@gmail.com
License: UNKNOWN
Project-URL: Bug Tracker, https://github.com/dftorres/mi_proyecto/issues
Platform: UNKNOWN
Classifier: Programming Language :: Python :: 3
Classifier: License :: OSI Approved :: MIT License
Classifier: Operating System :: OS Independent
Requires-Python: >=3.6
License-File: LICENSE.md
